{
  "username": "your_impartus_email@example.com",
  "password": "your_impartus_password",
  "baseUrl": "https://a.impartus.com/api",
  "quality": "720",
  "views": "both",
  "downloadLocation": "./downloads",
  "tempDirLocation": "./temp",
  "slides": false,
  "audioOnly": false,
  "audioFormat": "mp3",
  "skipNoAudio": false,
  "numWorkers": 5,
  "rateLimit": 100,
  "apiRateLimit": 2,
  "enablePipeline": false,
  "downloadWorkersPerLecture": 12,
  "decryptWorkersPerLecture": 4,
  "httpTimeout": "10m",
  "enableJitter": true,
  "listenAddr": "127.0.0.1",
  "allowRemoteAccess": false,
  "progressTracking": {
    "enabled": false,
    "showSpeed": false,
    "showETA": false,
    "updateInterval": "2s",
    "speedWindowSize": 10
  }
}
